LICENSE
MANIFEST.in
README.md
setup.py
oBIX/__init__.py
oBIX.egg-info/PKG-INFO
oBIX.egg-info/SOURCES.txt
oBIX.egg-info/dependency_links.txt
oBIX.egg-info/requires.txt
oBIX.egg-info/top_level.txt
oBIX/client/__init__.py
oBIX/client/__version__.py
oBIX/client/client.py
oBIX/common/__init__.py
oBIX/common/__version__.py
oBIX/common/data_type.py
oBIX/common/obix_object.py
oBIX/common/point.py
oBIX/common/util.py