Metadata-Version: 2.1
Name: oBIX
Version: 0.4.7
Summary: A client package for interacting with oBIX(Open Building Information Exchange)
Home-page: https://github.com/IUpdatable/oBIX
Author: IUpdatable
Author-email: IUpdatable@163.com
License: MIT
Platform: UNKNOWN
Classifier: License :: OSI Approved :: MIT License
Classifier: Programming Language :: Python
Classifier: Programming Language :: Python :: 3
Classifier: Programming Language :: Python :: 3.6
Classifier: Programming Language :: Python :: Implementation :: CPython
Classifier: Programming Language :: Python :: Implementation :: PyPy
Requires-Python: >=3.7.0
